streamlit_editorjs/__init__.py
streamlit_editorjs-0.1.0.dist-info/LICENSE
streamlit_editorjs-0.1.0.dist-info/METADATA
streamlit_editorjs-0.1.0.dist-info/WHEEL
streamlit_editorjs-0.1.0.dist-info/top_level.txt
streamlit_editorjs-0.1.0.dist-info/RECORD
