Metadata-Version: 2.1
Name: streamlit-editorjs
Version: 0.1.0
Summary: EDITORJS component for Streamlit
Home-page: https://github.com/caviri/streamlit-editorjs
Author: caviri
Author-email: 
Requires-Python: >=3.6
License-File: LICENSE
Requires-Dist: streamlit (>=0.63)
